powerhose
