Metadata-Version: 1.0
Name: powerhose
Version: 0.5
Summary: Implementation of the Request-Reply Broken pattern in ZMQ
Home-page: https://github.com/mozilla-services/powerhose
Author: Mozilla Services
Author-email: services-dev@mozilla.org
License: MPLv2.0
Platform: UNKNOWN
Classifier: Programming Language :: Python
Classifier: License :: OSI Approved :: Mozilla Public License 2.0 (MPL 2.0)
